nemotron_page_elements_v3/config.json
nemotron_page_elements_v3/model.py
nemotron_page_elements_v3/page_element_v3.py
nemotron_page_elements_v3/utils.py
nemotron_page_elements_v3/post_processing/__init__.py
nemotron_page_elements_v3/post_processing/page_elt_pp.py
nemotron_page_elements_v3/post_processing/text_pp.py
nemotron_page_elements_v3/post_processing/wbf.py
nemotron_page_elements_v3/yolox/boxes.py
nemotron_page_elements_v3/yolox/darknet.py
nemotron_page_elements_v3/yolox/network_blocks.py
nemotron_page_elements_v3/yolox/yolo_fpn.py
nemotron_page_elements_v3/yolox/yolo_head.py
nemotron_page_elements_v3/yolox/yolo_pafpn.py
nemotron_page_elements_v3/yolox/yolox.py
nemotron_page_elements_v3-3.0.1.dist-info/METADATA
nemotron_page_elements_v3-3.0.1.dist-info/WHEEL
nemotron_page_elements_v3-3.0.1.dist-info/top_level.txt
nemotron_page_elements_v3-3.0.1.dist-info/RECORD
