Metadata-Version: 2.4
Name: nemotron-page-elements-v3
Version: 3.0.1
Summary: NVIDIA Nemotron Page Elements v3: A specialized YOLOX-based object detection model for identifying tables, charts, infographics, titles, headers/footers, and text in document pages
Author-email: NVIDIA Corporation <boli@nvidia.com>, Theo Viel <tviel@nvidia.com>, Bo Liu <boli@nvidia.com>
Maintainer-email: Theo Viel <tviel@nvidia.com>, Bo Liu <boli@nvidia.com>
License: NVIDIA Open Model License
Project-URL: Homepage, https://huggingface.co/nvidia/nemotron-page-elements-v3
Project-URL: Documentation, https://huggingface.co/nvidia/nemotron-page-elements-v3
Project-URL: Repository, https://huggingface.co/nvidia/nemotron-page-elements-v3
Project-URL: Bug Tracker, https://huggingface.co/nvidia/nemotron-page-elements-v3/discussions
Project-URL: Model Card, https://huggingface.co/nvidia/nemotron-page-elements-v3
Keywords: object-detection,document-understanding,pdf-extraction,yolox,page-layout,nvidia,nemotron,deep-learning,computer-vision
Classifier: Development Status :: 5 - Production/Stable
Classifier: Intended Audience :: Developers
Classifier: Intended Audience :: Science/Research
Classifier: Topic :: Scientific/Engineering :: Artificial Intelligence
Classifier: Topic :: Scientific/Engineering :: Image Recognition
Classifier: License :: Other/Proprietary License
Classifier: Programming Language :: Python :: 3
Classifier: Programming Language :: Python :: 3.8
Classifier: Programming Language :: Python :: 3.9
Classifier: Programming Language :: Python :: 3.10
Classifier: Programming Language :: Python :: 3.11
Classifier: Programming Language :: Python :: 3.12
Requires-Python: >=3.8
Requires-Dist: numpy
Requires-Dist: torch>=1.7
Requires-Dist: opencv-python
Requires-Dist: loguru
Requires-Dist: tqdm
Requires-Dist: torchvision
Requires-Dist: thop
Requires-Dist: ninja
Requires-Dist: tabulate
Requires-Dist: psutil
Requires-Dist: tensorboard
Requires-Dist: pycocotools>=2.0.2
Requires-Dist: onnx>=1.13.0
Requires-Dist: huggingface_hub
Provides-Extra: dev
Requires-Dist: pytest>=7.0; extra == "dev"
Requires-Dist: black>=22.0; extra == "dev"
Requires-Dist: flake8>=4.0; extra == "dev"
Requires-Dist: mypy>=0.950; extra == "dev"
